MANIFEST.in
README.rst
setup.py
c2c/__init__.py
c2c.recipe.closurecompile.egg-info/PKG-INFO
c2c.recipe.closurecompile.egg-info/SOURCES.txt
c2c.recipe.closurecompile.egg-info/dependency_links.txt
c2c.recipe.closurecompile.egg-info/entry_points.txt
c2c.recipe.closurecompile.egg-info/namespace_packages.txt
c2c.recipe.closurecompile.egg-info/not-zip-safe
c2c.recipe.closurecompile.egg-info/requires.txt
c2c.recipe.closurecompile.egg-info/top_level.txt
c2c/recipe/__init__.py
c2c/recipe/closurecompile/__init__.py
c2c/recipe/closurecompile/buildout.py
c2c/recipe/closurecompile/depswriter.py
c2c/recipe/closurecompile/goog/__init__.py
c2c/recipe/closurecompile/goog/closurebuilder.py
c2c/recipe/closurecompile/goog/depstree.py
c2c/recipe/closurecompile/goog/depstree_test.py
c2c/recipe/closurecompile/goog/depswriter.py
c2c/recipe/closurecompile/goog/jscompiler.py
c2c/recipe/closurecompile/goog/source.py
c2c/recipe/closurecompile/goog/source_test.py
c2c/recipe/closurecompile/goog/treescan.py