Metadata-Version: 1.0
Name: c2c.recipe.closurecompile
Version: 0.3.1
Summary: A buildout recipe to compile javascript with the Google Closure Compiler
Home-page: https://github.com/camptocamp/c2c.recipe.closurecompile
Author: Frederic Junod
Author-email: frederic.junod@camptocamp.com
License: MIT License
Platform: UNKNOWN
Classifier: Development Status :: 2 - Pre-Alpha
Classifier: Framework :: Buildout
Classifier: Intended Audience :: Developers
Classifier: Topic :: Software Development :: Build Tools
Classifier: Topic :: Software Development :: Libraries :: Python Modules
Classifier: License :: OSI Approved :: MIT License
